iolink/__init__.py
iolink/misc.py
iolink/port.py
iolink/version.py
iolink/interfaces/__init__.py
iolink/interfaces/iqlink/__init__.py
iolink/interfaces/iqlink/iqlink.py
iolink-0.0.5.dist-info/LICENSE
iolink-0.0.5.dist-info/METADATA
iolink-0.0.5.dist-info/WHEEL
iolink-0.0.5.dist-info/top_level.txt
iolink-0.0.5.dist-info/RECORD
